urlssser/__init__.py
urlssser-0.2.dist-info/METADATA
urlssser-0.2.dist-info/WHEEL
urlssser-0.2.dist-info/top_level.txt
urlssser-0.2.dist-info/RECORD
