Metadata-Version: 2.4
Name: urlssser
Version: 0.2
Summary: Simple Scopper Library
Author: fuckkkkk you 2 3 4
Classifier: Programming Language :: Python :: 3
Requires-Python: >=3.6
Dynamic: author
Dynamic: classifier
Dynamic: requires-python
Dynamic: summary
